pybess/Arbitrage.py
pybess/Battery.py
pybess/Combiner.py
pybess/HistoricalOpt.py
pybess/Importer.py
pybess/__init__.py
pybess/utils.py
pybess-0.0.8.dist-info/METADATA
pybess-0.0.8.dist-info/WHEEL
pybess-0.0.8.dist-info/top_level.txt
pybess-0.0.8.dist-info/RECORD
