Metadata-Version: 2.1
Name: pybess
Version: 0.0.8
Summary: Energy Arbitrage for Battery Energy Storage Systems
Home-page: UNKNOWN
Author: Daniel Tam & Henry Blumentals
Author-email: daniel.tam07@gmail.com
License: UNKNOWN
Platform: UNKNOWN
Classifier: Programming Language :: Python :: 3
Classifier: License :: OSI Approved :: MIT License
Classifier: Operating System :: OS Independent
